mplstylize/__init__.py
mplstylize/cmaps.json
mplstylize/colors.json
mplstylize/mpl_tools.py
mplstylize/stylesheet.mplstyle
mplstylize/fonts/NotoSans-Bold.ttf
mplstylize/fonts/NotoSans-Italic.ttf
mplstylize/fonts/NotoSans-Regular.ttf
mplstylize/fonts/NotoSansMath-Regular.ttf
mplstylize-0.1.1.dist-info/METADATA
mplstylize-0.1.1.dist-info/WHEEL
mplstylize-0.1.1.dist-info/licenses/LICENSE
mplstylize-0.1.1.dist-info/RECORD
