Metadata-Version: 2.3
Name: mplstylize
Version: 0.1.1
Summary: Style utilities for matplotlib
Requires-Python: >=3.10
Requires-Dist: ipython>=8.30.0
Requires-Dist: matplotlib>=3.9.2
